webdriver_selector/__init__.py
webdriver_selector/webdrivers.py
webdriver_selector-1.1.3.dist-info/LICENSE
webdriver_selector-1.1.3.dist-info/METADATA
webdriver_selector-1.1.3.dist-info/WHEEL
webdriver_selector-1.1.3.dist-info/top_level.txt
webdriver_selector-1.1.3.dist-info/RECORD
