Metadata-Version: 2.1
Name: webdriver-selector
Version: 1.1.3
Summary: webdriver_selector automatically configures a selenium webdriver on all available system browsers
Home-page: https://github.com/sean-bailey/webdriver_selector
Author: Sean Bailey
Author-email: seanbailey518@gmail.com
License: UNKNOWN
Platform: UNKNOWN
Classifier: Programming Language :: Python :: 3
Classifier: License :: OSI Approved :: GNU Affero General Public License v3 or later (AGPLv3+)
Classifier: Operating System :: OS Independent
Requires-Python: >=3.6
License-File: LICENSE
Requires-Dist: beautifulsoup4 (==4.10.0)
Requires-Dist: selenium (==4.1.2)
Requires-Dist: user-agent (==0.1.10)
Requires-Dist: webdriver-manager (==3.5.3)
Requires-Dist: Unidecode (==1.3.3)
Requires-Dist: cchardet (==2.1.7)
